data/Grids/fliegeMaierNodes_1_30.mat
data/Grids/lebedevQuadratures_3_131.mat
data/Grids/maxDetPoints_1_200.mat
data/Grids/n_designs_1_124.mat
data/Grids/t_designs_1_21.mat
data/ls_layouts/Aalto_subset_C.json
data/ls_layouts/Dome_29.json
data/ls_layouts/Graz.json
data/ls_layouts/Partial_frontal.json
spaudiopy/__init__.py
spaudiopy/decoder.py
spaudiopy/grids.py
spaudiopy/io.py
spaudiopy/parsa.py
spaudiopy/plot.py
spaudiopy/process.py
spaudiopy/sig.py
spaudiopy/sph.py
spaudiopy/utils.py
spaudiopy-0.2.0.dist-info/licenses/LICENSE
spaudiopy-0.2.0.dist-info/METADATA
spaudiopy-0.2.0.dist-info/WHEEL
spaudiopy-0.2.0.dist-info/top_level.txt
spaudiopy-0.2.0.dist-info/zip-safe
spaudiopy-0.2.0.dist-info/RECORD
