Metadata-Version: 2.4
Name: spaudiopy
Version: 0.2.0
Summary: Spatial Audio Python Package
Home-page: https://github.com/chris-hld/spaudiopy
Author: Chris Hold
Author-email: Christoph.Hold@alumni.aalto.fi
License: MIT
Platform: any
Classifier: Development Status :: 3 - Alpha
Classifier: License :: OSI Approved :: MIT License
Classifier: Operating System :: OS Independent
Classifier: Programming Language :: Python
Classifier: Programming Language :: Python :: 3
Classifier: Programming Language :: Python :: 3 :: Only
Classifier: Topic :: Scientific/Engineering
Requires-Python: >=3.6
License-File: LICENSE
Requires-Dist: numpy
Requires-Dist: scipy
Requires-Dist: matplotlib!=3.1.*,!=3.2.*
Requires-Dist: soundfile
Requires-Dist: sounddevice
Requires-Dist: resampy
Requires-Dist: h5py
Dynamic: author
Dynamic: author-email
Dynamic: classifier
Dynamic: description
Dynamic: description-content-type
Dynamic: home-page
Dynamic: license
Dynamic: license-file
Dynamic: platform
Dynamic: requires-dist
Dynamic: requires-python
Dynamic: summary
